Workbook

Sheet 说明
A1: 建筑正式数值配置表
A2: 黄色单元格是策划输入，蓝色单元格是公式/检查。Unity 导表器是最终校验权威；任一错误会阻止整次导入。
A4: SchemaVersion | B4: 4
A5: 正式源路径 | B5: ConfigSource/Buildings/建筑数值策划表.xlsx（项目根目录，不进入 AssetDatabase）
A6: 当前家族数 | B6: =COUNTA(建筑家族!A5:A24) -> 9
A7: 当前运营等级数 | B7: =COUNTA(运营等级!A5:A24) -> 19
A8: 核心组合键 | B8: FamilyId + Level；作物增加 CropId；范围效果增加 EffectId；视觉增加 StyleId
A10: 数据权属
A11: Excel 导入 | B11: 建筑公共数值、放置/施工/升级消耗、运营等级、等级配置、仓库/市场/树木/范围效果/作物模块默认值
A12: Unity 维护 | B12: Runtime Prefab 结构、ModuleSet 模块结构、Presentation、图标/View、显示条件与复杂非科技条件
A13: Prefab 标量 | B13: 导表器只更新资源提供点、资源优先级、行动力预算三个数据字段，不添加/删除组件
A14: ItemId | B14: Excel 使用 ItemId；导入器解析后写入真实 ItemDefinition 引用
A15: 条件 | B15: 升级条件支持 none、keep、technology.<TechnologyId>；显示条件继续在 Unity 维护
A16: 视觉样式 | B16: 视觉样式工作表仅作美术回填清单，不参与数值导入，不会清空已有表现资源
A18: 策划流程
A19: 1 | B19: 在对应专表修改黄色输入字段；不要改工作表名、第 4 行列名或 SchemaVersion 位置。
A20: 2 | B20: 回到 Unity：Landsong / Building / 建筑数值导表工具。
A21: 3 | B21: 点击“重新读取并校验”，先修复全部错误。警告可根据内容判断。
A22: 4 | B22: 确认影响预览后执行导入；导入支持一次 Undo。
A23: 5 | B23: 新增建筑或模块结构仍先用建筑编辑器创建，再补本表数据。未知 FamilyId 不会自动创建资产。

Sheet 建筑家族
A1: 建筑家族（公共数值）
A2: 一行一个现有 FamilyId。FamilyId 是匹配键，不能用导表重命名；图标与显示条件不在本表。地形Keys 多项用 | 分隔。
A4: FamilyId | B4: 名称 | C4: 分类 | D4: SizeX | E4: SizeY | F4: 忽略地形 | G4: 地形Keys | H4: 移动阻力 | I4: 施工回合 | J4: 数量上限 | K4: 数量限制分组ID | L4: 蓝图初始锁定 | M4: 锁定时隐藏 | N4: 菜单排序 | O4: 开发完成 | P4: 资源提供点 | Q4: 资源提供优先级 | R4: 行动力预算 | S4: 说明
A5: building.player_home | B5: 王宫 | C5: 市政 | D5: 4 | E5: 4 | F5: 否 | G5: 陆地 | H5: 0 | I5: 1 | J5: 1 | K5: building.player_home | L5: 否 | M5: 否 | N5: 0 | O5: 是 | P5: 是 | Q5: 0 | R5: 100 | S5: 显示条件由 Unity 维护为隐藏；提供固定人口、库存与科技点
A6: building.residential_house | B6: 居民房 | C6: 人口 | D6: 1 | E6: 1 | F6: 否 | G6: 陆地 | H6: 0 | I6: 3 | J6: 99 | K6: building.residential_house | L6: 否 | M6: 否 | N6: 0 | O6: 是 | P6: 否 | Q6: 0 | R6: 100 | S6: 放置后经历 3 个施工阶段
A7: building.lumber_cabin | B7: 伐木小屋 | C7: 工业 | D7: 1 | E7: 1 | F7: 否 | G7: 陆地 | H7: 0 | I7: 1 | J7: 0 | K7: building.lumber_cabin | L7: 是 | M7: 是 | N7: 0 | O7: 是 | P7: 否 | Q7: 0 | R7: 100 | S7: 岗位 + 普通生产
A8: building.fishing_hut | B8: 捕鱼小屋 | C8: 农业 | D8: 2 | E8: 2 | F8: 否 | G8: 陆地 | H8: 0 | I8: 1 | J8: 0 | K8: building.fishing_hut | L8: 否 | M8: 否 | N8: 0 | O8: 否 | P8: 否 | Q8: 0 | R8: 100 | S8: 岗位 + 普通生产 + 稀有产出
A9: building.farm_field | B9: 农田 | C9: 农业 | D9: 2 | E9: 2 | F9: 否 | G9: 陆地 | H9: 0 | I9: 1 | J9: 0 | K9: building.farm_field | L9: 否 | M9: 否 | N9: 0 | O9: 是 | P9: 否 | Q9: 0 | R9: 100 | S9: 作物表当前为空，待策划配置
A10: building.market | B10: 市场 | C10: 经济 | D10: 1 | E10: 1 | F10: 否 | G10: 陆地 | H10: 0 | I10: 1 | J10: 0 | K10: building.market | L10: 否 | M10: 否 | N10: 0 | O10: 是 | P10: 是 | Q10: 10 | R10: 100 | S10: 满岗位时作为资源提供点并按价值结算金币
A11: building.warehouse | B11: 仓库 | C11: 人口|经济|工业 | D11: 2 | E11: 2 | F11: 否 | G11: 陆地 | H11: 0 | I11: 3 | J11: 0 | K11: building.warehouse | L11: 否 | M11: 否 | N11: 30 | O11: 是 | P11: 否 | Q11: 0 | R11: 100 | S11: 动态库存容量；维护费、经验和岗位阈值见等级_仓库
A12: building.road | B12: 泥路 | C12: 交通 | D12: 1 | E12: 1 | F12: 否 | G12: 陆地 | H12: 5 | I12: 1 | J12: 0 | K12: building.road | L12: 否 | M12: 否 | N12: 0 | O12: 是 | P12: 否 | Q12: 0 | R12: 100 | S12: 移动阻力 5
A13: building.tree | B13: 树木 | C13: 装饰 | D13: 1 | E13: 1 | F13: 否 | G13: 陆地 | H13: 0 | I13: 1 | J13: 0 | K13: building.tree | L13: 否 | M13: 否 | N13: 0 | O13: 是 | P13: 否 | Q13: 0 | R13: 100 | S13: 一个家族，八个视觉 Style

Sheet 放置消耗
A1: 放置消耗
A2: 确认放置时一次性扣除。一行一种 ItemId；无费用的建筑不写占位行。
A4: FamilyId | B4: ItemId | C4: 数量 | D4: 说明
A5: building.residential_house | B5: 金币 | C5: 30 | D5: 放下施工实例时支付
A6: building.residential_house | B6: 石头 | C6: 1 | D6: 放下施工实例时支付
A7: building.residential_house | B7: 原木 | C7: 1 | D7: 放下施工实例时支付
A8: building.tree | B8: 金币 | C8: 10 | D8: 所有 Tree Style 共用
A9: building.tree | B9: 树苗 | C9: 1 | D9: 所有 Tree Style 共用
A10: building.warehouse | B10: 金币 | C10: 30 | D10: 放下施工实例时支付

Sheet 施工消耗
A1: 逐回合施工消耗
A2: 回合序号从 1 开始，不能超过建筑家族表中的施工回合。空施工回合不写费用行。
A4: FamilyId | B4: 回合序号 | C4: ItemId | D4: 数量 | E4: 说明
A5: building.residential_house | B5: 1 | C5: 泥土 | D5: 10 | E5: 第 1 施工阶段
A6: building.residential_house | B6: 2 | C6: 石头 | D6: 10 | E6: 第 2 施工阶段
A7: building.residential_house | B7: 3 | C7: 原木 | D7: 10 | E7: 第 3 施工阶段
A8: building.warehouse | B8: 1 | C8: 泥土 | D8: 10 | E8: 第 1 施工阶段（粘土资产的稳定 ItemId 为泥土）
A9: building.warehouse | B9: 2 | C9: 原木 | D9: 10 | E9: 第 2 施工阶段（木材映射为基础资源原木）
A10: building.warehouse | B10: 3 | C10: 石头 | D10: 10 | E10: 第 3 施工阶段

Sheet 运营等级
A1: 运营等级与升级条件
A2: 一行一个 FamilyId + Level，必须从 LV1 连续。ConditionId 支持 none、keep、technology.<TechnologyId>。
A4: FamilyId | B4: Level | C4: 开放 | D4: ConditionId | E4: 说明
A5: building.player_home | B5: 1 | C5: 是 | D5: none | E5: 施工完成进入 LV1
A6: building.player_home | B6: 2 | C6: 否 | D6: none | E6: 占位等级，开放前需补条件与数值
A7: building.player_home | B7: 3 | C7: 否 | D7: none | E7: 占位等级，开放前需补条件与数值
A8: building.player_home | B8: 4 | C8: 否 | D8: none | E8: 占位等级，开放前需补条件与数值
A9: building.residential_house | B9: 1 | C9: 是 | D9: none | E9: 施工完成进入 LV1
A10: building.residential_house | B10: 2 | C10: 否 | D10: none | E10: 占位等级
A11: building.residential_house | B11: 3 | C11: 否 | D11: none | E11: 占位等级
A12: building.residential_house | B12: 4 | C12: 否 | D12: none | E12: 占位等级
A13: building.lumber_cabin | B13: 1 | C13: 是 | D13: none | E13: 施工完成进入 LV1
A14: building.lumber_cabin | B14: 2 | C14: 是 | D14: technology.TN_3_1_启蒙 | E14: 满足科技并支付升级费用
A15: building.fishing_hut | B15: 1 | C15: 是 | D15: none | E15: 施工完成进入 LV1
A16: building.fishing_hut | B16: 2 | C16: 否 | D16: none | E16: 占位等级
... A23: building.tree | B23: 1 | C23: 是 | D23: none | E23: 施工完成进入 LV1

Sheet 升级消耗
A1: 升级消耗（目标等级口径）
A2: 费用写在升入的目标等级上。LV1 不允许写升级费用。
A4: FamilyId | B4: 目标Level | C4: ItemId | D4: 数量 | E4: 说明
A5: building.lumber_cabin | B5: 2 | C5: 金币 | D5: 30 | E5: 需同时满足 technology.TN_3_1_启蒙

Sheet 等级_固定人口
A1: 等级配置：固定人口
A2: 对应 PlayerHomeLevelConfiguration；只允许拥有 population.fixed 模块的家族填写。
A4: FamilyId | B4: Level | C4: 提供人口 | D4: 校验
A5: building.player_home | B5: 1 | C5: 10 | D5: =IF(COUNTIFS(运营等级!$A$5:$A$24,A5,运营等级!$B$5:$B$24,B5)=0,"错误：缺少等级","通过") -> 通过
A6: building.player_home | B6: 2 | C6: 10 | D6: =IF(COUNTIFS(运营等级!$A$5:$A$24,A6,运营等级!$B$5:$B$24,B6)=0,"错误：缺少等级","通过") -> 通过
A7: building.player_home | B7: 3 | C7: 10 | D7: =IF(COUNTIFS(运营等级!$A$5:$A$24,A7,运营等级!$B$5:$B$24,B7)=0,"错误：缺少等级","通过") -> 通过
A8: building.player_home | B8: 4 | C8: 10 | D8: =IF(COUNTIFS(运营等级!$A$5:$A$24,A8,运营等级!$B$5:$B$24,B8)=0,"错误：缺少等级","通过") -> 通过

Sheet 等级_库存容量
A1: 等级配置：库存容量
A2: 对应 BuildingInventoryLevelConfiguration；单位为库存格。
A4: FamilyId | B4: Level | C4: 提供库存格 | D4: 校验
A5: building.player_home | B5: 1 | C5: 5 | D5: =IF(COUNTIFS(运营等级!$A$5:$A$24,A5,运营等级!$B$5:$B$24,B5)=0,"错误：缺少等级","通过") -> 通过
A6: building.player_home | B6: 2 | C6: 5 | D6: =IF(COUNTIFS(运营等级!$A$5:$A$24,A6,运营等级!$B$5:$B$24,B6)=0,"错误：缺少等级","通过") -> 通过
A7: building.player_home | B7: 3 | C7: 5 | D7: =IF(COUNTIFS(运营等级!$A$5:$A$24,A7,运营等级!$B$5:$B$24,B7)=0,"错误：缺少等级","通过") -> 通过
A8: building.player_home | B8: 4 | C8: 5 | D8: =IF(COUNTIFS(运营等级!$A$5:$A$24,A8,运营等级!$B$5:$B$24,B8)=0,"错误：缺少等级","通过") -> 通过

Sheet 等级_科技点
A1: 等级配置：科技点
A2: 对应 BuildingTechnologyPointLevelConfiguration；每个成功回合注入当前研究。
A4: FamilyId | B4: Level | C4: 科技点/回合 | D4: 校验
A5: building.player_home | B5: 1 | C5: 1 | D5: =IF(COUNTIFS(运营等级!$A$5:$A$24,A5,运营等级!$B$5:$B$24,B5)=0,"错误：缺少等级","通过") -> 通过
A6: building.player_home | B6: 2 | C6: 1 | D6: =IF(COUNTIFS(运营等级!$A$5:$A$24,A6,运营等级!$B$5:$B$24,B6)=0,"错误：缺少等级","通过") -> 通过
A7: building.player_home | B7: 3 | C7: 1 | D7: =IF(COUNTIFS(运营等级!$A$5:$A$24,A7,运营等级!$B$5:$B$24,B7)=0,"错误：缺少等级","通过") -> 通过
A8: building.player_home | B8: 4 | C8: 1 | D8: =IF(COUNTIFS(运营等级!$A$5:$A$24,A8,运营等级!$B$5:$B$24,B8)=0,"错误：缺少等级","通过") -> 通过

Sheet 等级_住宅
A1: 等级配置：居民运营
A2: 对应 ResidentialHousingLevelConfiguration。食物按当前人口每回合消耗，满人口食物/回合是公式提示，不参与导入。
A4: FamilyId | B4: Level | C4: 初始人口 | D4: 人口上限 | E4: FoodItemId | F4: 增长回合 | G4: 失败衰减阈值 | H4: TaxItemId | I4: 税收回合 | J4: 满人口食物/回合 | K4: 校验
A5: building.residential_house | B5: 1 | C5: 2 | D5: 5 | E5: 蔬菜 | F5: 3 | G5: 3 | H5: 金币 | I5: 5 | J5: =D5 -> 5 | K5: =IF(D5<C5,"错误：人口上限","通过") -> 通过
A6: building.residential_house | B6: 2 | C6: 2 | D6: 5 | E6: 蔬菜 | F6: 3 | G6: 3 | H6: 金币 | I6: 5 | J6: =D6 -> 5 | K6: =IF(D6<C6,"错误：人口上限","通过") -> 通过
A7: building.residential_house | B7: 3 | C7: 2 | D7: 5 | E7: 蔬菜 | F7: 3 | G7: 3 | H7: 金币 | I7: 5 | J7: =D7 -> 5 | K7: =IF(D7<C7,"错误：人口上限","通过") -> 通过
A8: building.residential_house | B8: 4 | C8: 2 | D8: 5 | E8: 蔬菜 | F8: 3 | G8: 3 | H8: 金币 | I8: 5 | J8: =D8 -> 5 | K8: =IF(D8<C8,"错误：人口上限","通过") -> 通过

Sheet 等级_岗位
A1: 等级配置：岗位运营
A2: 对应 BuildingWorkforceLevelConfiguration。每个拥有 workforce 模块的运营等级必须恰好一行。
A4: FamilyId | B4: Level | C4: 最大工人 | D4: 初始工人 | E4: 基础吸引力 | F4: 招工金币 | G4: 自动补贴 | H4: 稳定目标工人 | I4: GoldItemId | J4: 校验
A5: building.lumber_cabin | B5: 1 | C5: 3 | D5: 2 | E5: 55 | F5: 10 | G5: 否 | H5: 0 | I5: 金币 | J5: =IF(OR(D5>C5,H5>C5),"错误：工人超上限","通过") -> 通过
A6: building.lumber_cabin | B6: 2 | C6: 5 | D6: 2 | E6: 55 | F6: 10 | G6: 否 | H6: 0 | I6: 金币 | J6: =IF(OR(D6>C6,H6>C6),"错误：工人超上限","通过") -> 通过
A7: building.fishing_hut | B7: 1 | C7: 3 | D7: 0 | E7: 55 | F7: 10 | G7: 否 | H7: 0 | I7: 金币 | J7: =IF(OR(D7>C7,H7>C7),"错误：工人超上限","通过") -> 通过
A8: building.fishing_hut | B8: 2 | C8: 3 | D8: 0 | E8: 55 | F8: 10 | G8: 否 | H8: 0 | I8: 金币 | J8: =IF(OR(D8>C8,H8>C8),"错误：工人超上限","通过") -> 通过
A9: building.farm_field | B9: 1 | C9: 2 | D9: 0 | E9: 55 | F9: 10 | G9: 否 | H9: 0 | I9: 金币 | J9: =IF(OR(D9>C9,H9>C9),"错误：工人超上限","通过") -> 通过
A10: building.market | B10: 1 | C10: 3 | D10: 3 | E10: 100 | F10: 10 | G10: 是 | H10: 3 | I10: 金币 | J10: =IF(OR(D10>C10,H10>C10),"错误：工人超上限","通过") -> 通过
A11: building.warehouse | B11: 1 | C11: 2 | D11: 0 | E11: 55 | F11: 10 | G11: 否 | H11: 0 | I11: 金币 | J11: =IF(OR(D11>C11,H11>C11),"错误：工人超上限","通过") -> 通过
A12: building.warehouse | B12: 2 | C12: 3 | D12: 0 | E12: 55 | F12: 10 | G12: 否 | H12: 0 | I12: 金币 | J12: =IF(OR(D12>C12,H12>C12),"错误：工人超上限","通过") -> 通过
A13: building.warehouse | B13: 3 | C13: 5 | D13: 0 | E13: 55 | F13: 10 | G13: 否 | H13: 0 | I13: 金币 | J13: =IF(OR(D13>C13,H13>C13),"错误：工人超上限","通过") -> 通过

Sheet 等级_生产
A1: 等级配置：资源产出
A2: 一行一个 FamilyId + Level + OutputItemId + 工人阈值。同一等级的周期回合必须一致；产量/回合是公式，不参与导入。
A4: FamilyId | B4: Level | C4: OutputItemId | D4: 工人阈值 | E4: 产量/周期 | F4: 周期回合 | G4: 产量/回合 | H4: 校验
A5: building.lumber_cabin | B5: 1 | C5: 原木 | D5: 2 | E5: 1 | F5: 3 | G5: =E5/F5 -> 0.33333333 | H5: =IF(COUNTIFS(等级_岗位!$A$5:$A$24,A5,等级_岗位!$B$5:$B$24,B5)=0,"错误：缺少岗位","通过") -> 通过
A6: building.lumber_cabin | B6: 1 | C6: 原木 | D6: 3 | E6: 2 | F6: 3 | G6: =E6/F6 -> 0.66666667 | H6: =IF(COUNTIFS(等级_岗位!$A$5:$A$24,A6,等级_岗位!$B$5:$B$24,B6)=0,"错误：缺少岗位","通过") -> 通过
A7: building.lumber_cabin | B7: 2 | C7: 原木 | D7: 2 | E7: 1 | F7: 3 | G7: =E7/F7 -> 0.33333333 | H7: =IF(COUNTIFS(等级_岗位!$A$5:$A$24,A7,等级_岗位!$B$5:$B$24,B7)=0,"错误：缺少岗位","通过") -> 通过
A8: building.lumber_cabin | B8: 2 | C8: 原木 | D8: 3 | E8: 2 | F8: 3 | G8: =E8/F8 -> 0.66666667 | H8: =IF(COUNTIFS(等级_岗位!$A$5:$A$24,A8,等级_岗位!$B$5:$B$24,B8)=0,"错误：缺少岗位","通过") -> 通过
A9: building.lumber_cabin | B9: 2 | C9: 原木 | D9: 5 | E9: 4 | F9: 3 | G9: =E9/F9 -> 1.3333333 | H9: =IF(COUNTIFS(等级_岗位!$A$5:$A$24,A9,等级_岗位!$B$5:$B$24,B9)=0,"错误：缺少岗位","通过") -> 通过
A10: building.fishing_hut | B10: 1 | C10: 鱼 | D10: 2 | E10: 1 | F10: 3 | G10: =E10/F10 -> 0.33333333 | H10: =IF(COUNTIFS(等级_岗位!$A$5:$A$24,A10,等级_岗位!$B$5:$B$24,B10)=0,"错误：缺少岗位","通过") -> 通过
A11: building.fishing_hut | B11: 1 | C11: 鱼 | D11: 3 | E11: 2 | F11: 3 | G11: =E11/F11 -> 0.66666667 | H11: =IF(COUNTIFS(等级_岗位!$A$5:$A$24,A11,等级_岗位!$B$5:$B$24,B11)=0,"错误：缺少岗位","通过") -> 通过
A12: building.fishing_hut | B12: 2 | C12: 鱼 | D12: 2 | E12: 1 | F12: 3 | G12: =E12/F12 -> 0.33333333 | H12: =IF(COUNTIFS(等级_岗位!$A$5:$A$24,A12,等级_岗位!$B$5:$B$24,B12)=0,"错误：缺少岗位","通过") -> 通过
A13: building.fishing_hut | B13: 2 | C13: 鱼 | D13: 3 | E13: 2 | F13: 3 | G13: =E13/F13 -> 0.66666667 | H13: =IF(COUNTIFS(等级_岗位!$A$5:$A$24,A13,等级_岗位!$B$5:$B$24,B13)=0,"错误：缺少岗位","通过") -> 通过

Sheet 等级_捕鱼稀有
A1: 等级配置：捕鱼稀有产出
A2: 对应 FishingHutLevelConfiguration / BM_稀有产出。禁用时仍可保留 ItemId 作为未来占位。
A4: FamilyId | B4: Level | C4: 启用 | D4: ItemId | E4: 最低工人 | F4: 概率% | G4: 数量 | H4: 校验
A5: building.fishing_hut | B5: 1 | C5: 否 | D5: 黄金鱼 | E5: 3 | F5: 1 | G5: 1 | H5: =IF(OR(F5<0,F5>100),"错误：概率范围","通过") -> 通过
A6: building.fishing_hut | B6: 2 | C6: 否 | D6: 黄金鱼 | E6: 3 | F6: 1 | G6: 1 | H6: =IF(OR(F6<0,F6>100),"错误：概率范围","通过") -> 通过

Sheet 等级_仓库
A1: 等级配置：仓库运营
A2: 对应 WarehouseLevelConfiguration / BM_仓库运营。基础库存格只在达到容量所需工人时生效；维护失败会阻止经验并降低本建筑岗位吸引力。
A4: FamilyId | B4: Level | C4: 容量所需工人 | D4: 基础库存格 | E4: MaintenanceItemId | F4: 维护费/回合 | G4: 经验所需工人 | H4: 经验/回合 | I4: 下级经验要求 | J4: 奖励工人阈值 | K4: 奖励库存格 | L4: 维护失败吸引力惩罚 | M4: 校验
A5: building.warehouse | B5: 1 | C5: 2 | D5: 1 | E5: 金币 | F5: 1 | G5: 2 | H5: 1 | I5: 30 | J5: 0 | K5: 0 | L5: 10 | M5: =IF(COUNTIFS(等级_岗位!$A$5:$A$24,A5,等级_岗位!$B$5:$B$24,B5)=0,"错误：缺少岗位",IF(MAX(C5,G5,J5)>SUMIFS(等级_岗位!$C$5:$C$24,等级_岗位!$A$5:$A$24,A5,等级_岗位!$B$5:$B$24,B5),"错误：阈值超上限","通过")) -> 通过
A6: building.warehouse | B6: 2 | C6: 3 | D6: 2 | E6: 金币 | F6: 2 | G6: 2 | H6: 1 | I6: 50 | J6: 0 | K6: 0 | L6: 10 | M6: =IF(COUNTIFS(等级_岗位!$A$5:$A$24,A6,等级_岗位!$B$5:$B$24,B6)=0,"错误：缺少岗位",IF(MAX(C6,G6,J6)>SUMIFS(等级_岗位!$C$5:$C$24,等级_岗位!$A$5:$A$24,A6,等级_岗位!$B$5:$B$24,B6),"错误：阈值超上限","通过")) -> 通过
A7: building.warehouse | B7: 3 | C7: 4 | D7: 3 | E7: 金币 | F7: 3 | G7: 0 | H7: 0 | I7: 0 | J7: 5 | K7: 1 | L7: 10 | M7: =IF(COUNTIFS(等级_岗位!$A$5:$A$24,A7,等级_岗位!$B$5:$B$24,B7)=0,"错误：缺少岗位",IF(MAX(C7,G7,J7)>SUMIFS(等级_岗位!$C$5:$C$24,等级_岗位!$A$5:$A$24,A7,等级_岗位!$B$5:$B$24,B7),"错误：阈值超上限","通过")) -> 通过

Sheet 模块_市场
A1: 模块默认值：市场资源结算
A2: 模块级配置，不随运营等级变化。价值结算比例以小数填写：0.1 表示 10%。
A4: FamilyId | B4: GoldItemId | C4: 价值结算比例 | D4: 显示比例 | E4: 校验
A5: building.market | B5: 金币 | C5: 0.1 | D5: =C5 -> 0.1 | E5: =IF(C5<0,"错误：比例","通过") -> 通过

Sheet 模块_树木
A1: 模块默认值：树木采集
A2: 模块级配置，不随运营等级或 Style 变化。平均生命与预计双击次数为策划分析公式。
A4: FamilyId | B4: 最低生命 | C4: 最高生命 | D4: 双击伤害 | E4: WoodItemId | F4: 原木奖励 | G4: SaplingItemId | H4: 树苗奖励 | I4: 平均生命 | J4: 预计双击次数 | K4: 校验
A5: building.tree | B5: 3 | C5: 6 | D5: 1 | E5: 原木 | F5: 2 | G5: 树苗 | H5: 3 | I5: =(B5+C5)/2 -> 4.5 | J5: =ROUNDUP(I5/D5,0) -> 5 | K5: =IF(C5<B5,"错误：生命范围","通过") -> 通过

Sheet 模块_范围效果
A1: 模块默认值：范围效果
A2: 一行一个 FamilyId + EffectId。先在 Unity 中创建效果资产并挂入 ModuleSet；本表管理效果类型、目标、范围、数值及叠加规则。
A4: FamilyId | B4: EffectId | C4: 显示名 | D4: Kind | E4: TargetFilter | F4: 曼哈顿半径 | G4: 效果数值 | H4: StackingRule | I4: 影响自身占地 | J4: 覆盖格说明 | K4: 校验
A5: building.tree | B5: beauty.tree | C5: 树木美化 | D5: beauty | E5: cell | F5: 4 | G5: 1 | H5: highest_value | I5: 否 | J5: =IF(AND(D5="beauty",E5="cell",F5=1,G5=1,I5="否"),"正交四邻格各 +1","按当前参数计算") -> 按当前参数计算 | K5: =IF(OR(F5<0,G5<=0,AND(I5="否",F5<1)),"错误：范围/数值",IF(AND(D5="beauty",E5<>"cell"),"错误：美化目标","通过")) -> 通过

Sheet 模块_作物
A1: 模块默认值：作物定义
A2: 当前项目作物列表尚未配置。新增时一行一个 FamilyId + CropId；图标继续在 Unity 中按 CropId 维护，导入不会覆盖。
A4: FamilyId | B4: CropId | C4: 显示名 | D4: 成熟回合 | E4: 说明

Sheet 作物_种植消耗
A1: 作物：种植消耗
A2: 引用模块_作物中的 FamilyId + CropId。一行一种 ItemId；无消耗不写行。
A4: FamilyId | B4: CropId | C4: ItemId | D4: 数量 | E4: 说明

Sheet 作物_收获产出
A1: 作物：收获产出
A2: 引用模块_作物中的 FamilyId + CropId。一行一种 ItemId，最小/最大数量形成随机区间。
A4: FamilyId | B4: CropId | C4: ItemId | D4: 最小数量 | E4: 最大数量 | F4: 说明

Sheet 作物_自动收获
A1: 作物：自动收获消耗
A2: 模块级自动收获费用，一行一种 ItemId；无费用不写行。
A4: FamilyId | B4: ItemId | C4: 数量 | D4: 说明

Sheet 视觉样式
A1: 视觉 Style 回填清单（不参与导入）
A2: Style 不产生新建筑家族。此表仅帮助策划与美术跟踪菜单名称、Icon 和各等级 View；实际引用仍在 BuildingPresentationDefinition。
A4: FamilyId | B4: StyleId | C4: 菜单名称 | D4: IconAssetPath | E4: LV1ViewAssetPath | F4: 回填状态
A5: building.tree | B5: tree_01 | C5: 树木 1 | F5: =IF(OR(D5="",E5=""),"待回填","完整") -> 待回填
A6: building.tree | B6: tree_02 | C6: 树木 2 | F6: =IF(OR(D6="",E6=""),"待回填","完整") -> 待回填
A7: building.tree | B7: tree_03 | C7: 树木 3 | F7: =IF(OR(D7="",E7=""),"待回填","完整") -> 待回填
A8: building.tree | B8: tree_04 | C8: 树木 4 | F8: =IF(OR(D8="",E8=""),"待回填","完整") -> 待回填
A9: building.tree | B9: tree_05 | C9: 树木 5 | F9: =IF(OR(D9="",E9=""),"待回填","完整") -> 待回填
A10: building.tree | B10: tree_06 | C10: 树木 6 | F10: =IF(OR(D10="",E10=""),"待回填","完整") -> 待回填
A11: building.tree | B11: tree_07 | C11: 树木 7 | F11: =IF(OR(D11="",E11=""),"待回填","完整") -> 待回填
A12: building.tree | B12: tree_08 | C12: 树木 8 | F12: =IF(OR(D12="",E12=""),"待回填","完整") -> 待回填

Sheet 数据字典
A1: 稳定 ID 与导入权属字典
A2: ItemId 与 TechnologyId 必须能在 Unity 项目中唯一解析；显示名称可以变化，稳定 ID 不应随文案调整。
A4: 类型 | B4: 稳定ID/名称 | C4: 显示说明 | D4: Unity 解析目标 | E4: 是否导入
A5: Category | B5: 人口 | C5: 住宅、人口容量与人口服务 | D5: BuildingCategory.人口 | E5: 是
A6: Category | B6: 农业 | C6: 种植、养殖、捕鱼与食物获取 | D6: BuildingCategory.农业 | E6: 是
A7: Category | B7: 工业 | C7: 资源采集、加工与制造 | D7: BuildingCategory.工业 | E7: 是
A8: Category | B8: 经济 | C8: 市场、贸易与财政 | D8: BuildingCategory.经济 | E8: 是
A9: Category | B9: 科研 | C9: 研究与科技产出 | D9: BuildingCategory.科研 | E9: 是
A10: Category | B10: 市政 | C10: 治理、公共服务与城市核心 | D10: BuildingCategory.市政 | E10: 是
A11: Category | B11: 军事 | C11: 防御、驻军与训练 | D11: BuildingCategory.军事 | E11: 是
A12: Category | B12: 交通 | C12: 道路、运输与通行设施 | D12: BuildingCategory.交通 | E12: 是
A13: Category | B13: 装饰 | C13: 景观与非核心装饰 | D13: BuildingCategory.装饰 | E13: 是
A14: Category | B14: 奇观 | C14: 唯一性或里程碑大型建筑 | D14: BuildingCategory.奇观 | E14: 是
A15: Item | B15: 金币 | C15: 金币 | D15: ItemDefinition.ItemId | E15: 是
... A39: Structure | B39: Runtime Prefab | C39: 组件与层级结构 | D39: Prefab | E39: 否

Sheet 汇总检查
A1: 正式源表汇总
A2: 这里提供快速体检，不替代 Unity 导表器。Unity 会额外检查重复键、物品/科技引用、等级连续性、模块依赖和数值范围。
A4: 检查项 | B4: 当前值 | C4: 基准/规则 | D4: 状态 | E4: 说明
A5: 家族数量 | B5: =COUNTA(建筑家族!A5:A24) -> 9 | C5: 9 | D5: =IF(B5=C5,"通过","待检查") -> 通过 | E5: 当前项目正式家族
A6: 运营等级数量 | B6: =COUNTA(运营等级!A5:A24) -> 19 | C6: 19 | D6: =IF(B6=C6,"通过","待检查") -> 通过 | E6: 含未开放占位等级
A7: 生产档位行数 | B7: =COUNTA(等级_生产!A5:A24) -> 9 | C7: 9 | D7: =IF(B7=C7,"通过","待检查") -> 通过 | E7: 伐木 5 行，捕鱼 4 行
A8: 范围效果行数 | B8: =COUNTA(模块_范围效果!A5:A24) -> 1 | C8: 1 | D8: =IF(B8=C8,"通过","待检查") -> 通过 | E8: 当前树木提供一条美化效果
A9: 仓库等级行数 | B9: =COUNTA(等级_仓库!A5:A24) -> 3 | C9: 3 | D9: =IF(B9=C9,"通过","待检查") -> 通过 | E9: LV1-LV3 均有仓库运营配置
A10: Style 待回填数 | B10: =COUNTIF(视觉样式!F5:F24,"待回填") -> 8 | C10: 0 | D10: =IF(B10=C10,"通过","待检查") -> 待检查 | E10: 美术回填不阻止数值导入
A11: SchemaVersion | B11: =说明!B4 -> 4 | C11: 4 | D11: =IF(B11=C11,"通过","待检查") -> 通过 | E11: 新增仓库等级正式导入；必须与 Unity 导表器一致
